{
    "relationships": [
        {
            "relationshipId": 1,
            "relationshipName": "instEmployee",
            "otherEntityName": "instEmployee",
            "relationshipType": "many-to-one",
            "otherEntityField": "name"
        },
        {
            "relationshipId": 2,
            "relationshipName": "payScale",
            "otherEntityName": "payScale",
            "relationshipType": "many-to-0ne",
            "otherEntityField": "code",
            "ownerSide": true
        }

    ],

    "fields": [

        {
            "fieldId": 1,
            "fieldName": "activationDate",
            "fieldType": "LocalDate"

        }, {
            "fieldId": 2,
            "fieldName": "endDate",
            "fieldType": "LocalDate"

        }

    ],
    "changelogDate": "20151207194609",
    "dto": "no",
    "pagination": "pagination"
}
