{
    "relationships": [
        {
            "relationshipId": 1,
            "relationshipName": "instEmployee",
            "otherEntityName": "instEmployee",
            "relationshipType": "many-to-one",
            "otherEntityField": "name"
        }
    ],
    "fields": [

        {
            "fieldId": 1,
            "fieldName": "date",
            "fieldType": "LocalDate"

        },
        {
            "fieldId": 2,
            "fieldName": "indexNo",
            "fieldType": "String",
            "fieldValidateRules": [
                "maxlength"
            ],
            "fieldValidateRulesMaxlength": "20"
        },
        {
            "fieldId": 3,
            "fieldName": "status",
            "fieldType": "Integer"
        }
    ],
    "changelogDate": "20151124222518",
    "dto": "no",
    "pagination": "pagination"
}
